datastore.cloudfiles-0.0.2-py2.7-nspkg.pth
datastore/cloudfiles/__init__.py
datastore/cloudfiles/test.py
datastore.cloudfiles-0.0.2.dist-info/DESCRIPTION.rst
datastore.cloudfiles-0.0.2.dist-info/METADATA
datastore.cloudfiles-0.0.2.dist-info/metadata.json
datastore.cloudfiles-0.0.2.dist-info/namespace_packages.txt
datastore.cloudfiles-0.0.2.dist-info/RECORD
datastore.cloudfiles-0.0.2.dist-info/top_level.txt
datastore.cloudfiles-0.0.2.dist-info/WHEEL
