Metadata-Version: 2.0
Name: datastore.cloudfiles
Version: 0.0.2
Summary: Rackspace Cloud Files implementation of Datastore.
Home-page: https://github.com/boilerroomtv/datastore.cloudfiles
Author: Ben Jeffrey
Author-email: ben.jeffrey@boilerroom.tv
License: MPL 2.0
Keywords: datastore,rackspace,cloud files,cloudfilespyraxstorage
Platform: UNKNOWN
Classifier: Environment :: OpenStack
Classifier: Intended Audience :: Developers
Classifier: Intended Audience :: System Administrators
Classifier: Topic :: Database
Classifier: Topic :: Database :: Front-Ends
Classifier: License :: OSI Approved :: Mozilla Public License 2.0 (MPL 2.0)
Classifier: Operating System :: OS Independent
Classifier: Development Status :: 3 - Alpha
Classifier: Programming Language :: Python
Classifier: Programming Language :: Python :: 2
Classifier: Programming Language :: Python :: 2.7
Requires-Dist: datastore (>=0.3)
Requires-Dist: pyrax (>=1.9)
